tests/__init__.py
tests/test_channel.py
tests/test_dummy.py
tests/test_playlist.py
tests/test_video.py
youtube_data_api3/__init__.py
youtube_data_api3/channel.py
youtube_data_api3/playlist.py
youtube_data_api3/video.py
youtube_data_api3-0.0.10.dist-info/DESCRIPTION.rst
youtube_data_api3-0.0.10.dist-info/METADATA
youtube_data_api3-0.0.10.dist-info/RECORD
youtube_data_api3-0.0.10.dist-info/WHEEL
youtube_data_api3-0.0.10.dist-info/metadata.json
youtube_data_api3-0.0.10.dist-info/top_level.txt
